claming/__init__.py
claming/claming.py
claming-1.5.dist-info/LICENSE
claming-1.5.dist-info/METADATA
claming-1.5.dist-info/WHEEL
claming-1.5.dist-info/top_level.txt
claming-1.5.dist-info/RECORD
