Metadata-Version: 2.1
Name: claming
Version: 1.5
Summary: A Python package for Cleansing Matching
Home-page: UNKNOWN
Author: agistyaanugrah
License: MIT
Platform: UNKNOWN
Requires-Dist: strsimpy
